progressionpicturepal/__init__.py
progressionpicturepal/flow.py
progressionpicturepal-0.3.0.dist-info/licenses/LICENSE
progressionpicturepal-0.3.0.dist-info/METADATA
progressionpicturepal-0.3.0.dist-info/WHEEL
progressionpicturepal-0.3.0.dist-info/top_level.txt
progressionpicturepal-0.3.0.dist-info/RECORD
